{"content":[{"id":"94049","settings":{"flex_direction":"column","min_height":{"unit":"vh","size":100,"sizes":[]},"background_background":"classic","background_image":{"url":"","id":"","size":"","alt":"Hero-background","source":"library"},"background_position":"bottom center","background_repeat":"no-repeat","background_size":"cover","background_overlay_background":"classic","background_overlay_image":{"url":"http:\/\/brightspark.local\/wp-content\/uploads\/2026\/04\/Fondo-hero1-1-scaled.png","id":654,"size":"","alt":"Hero-background","source":"library"},"background_overlay_position":"bottom center","background_overlay_repeat":"no-repeat","background_overlay_size":"cover","background_overlay_opacity":{"unit":"px","size":1,"sizes":[]},"__globals__":{"background_color":"","background_color_b":"globals\/colors?id=astglobalcolor0"},"container_type":"grid","boxed_width":{"unit":"px","size":1200,"sizes":[]},"grid_columns_grid":{"unit":"fr","size":2,"sizes":[]},"grid_rows_grid":{"unit":"fr","size":1,"sizes":[]},"grid_justify_items":"center","grid_align_items":"center","border_radius":{"unit":"px","top":"0","right":"0","bottom":"128","left":"0","isLinked":false},"presetTitle":"Grid","presetIcon":"eicon-container-grid","min_height_tablet":{"unit":"vh","size":"","sizes":[]},"min_height_mobile":{"unit":"vh","size":"","sizes":[]},"background_color_b":"#0ecbf1","margin":{"unit":"px","top":"-44","right":"0","bottom":"0","left":"0","isLinked":false},"width":{"unit":"%","size":100},"_flex_size":"none","_element_width":"initial","background_color":"#FFCCB8"},"elements":[{"id":"50e10dba","settings":{"classes":{"$$type":"classes","value":["e-50e10dba-2c1e927"]}},"elements":[{"id":"172e4305","settings":{"classes":{"$$type":"classes","value":["e-172e4305-ef30ee1"]},"paragraph":{"$$type":"html-v3","value":{"content":{"$$type":"string","value":"BrightSpark Creative Studio"},"children":[]}},"link":{"$$type":"link","value":[]}},"elements":[],"isInner":false,"widgetType":"e-paragraph","elType":"widget","styles":{"e-172e4305-ef30ee1":{"id":"e-172e4305-ef30ee1","label":"local","type":"class","variants":[{"meta":{"breakpoint":"desktop","state":null},"props":{"font-size":{"$$type":"size","value":{"unit":"px","size":14}},"color":{"$$type":"global-color-variable","value":"e-gv-4edbd6c"},"padding":{"$$type":"dimensions","value":{"block-start":{"$$type":"size","value":{"unit":"px","size":5}},"inline-end":{"$$type":"size","value":{"unit":"px","size":15}},"block-end":{"$$type":"size","value":{"unit":"px","size":5}},"inline-start":{"$$type":"size","value":{"unit":"px","size":15}}}},"border-radius":{"$$type":"size","value":{"unit":"px","size":24}},"border-width":{"$$type":"size","value":{"unit":"px","size":1}},"border-color":{"$$type":"global-color-variable","value":"e-gv-4edbd6c"},"border-style":{"$$type":"string","value":"solid"},"background":{"$$type":"background","value":{"color":{"$$type":"color","value":"#ffab8a70"}}},"align-self":{"$$type":"string","value":"start"}},"custom_css":null}]}},"interactions":[],"editor_settings":[],"version":"0.0"},{"id":"37b88a51","settings":{"classes":{"$$type":"classes","value":["e-37b88a51-1396f18"]},"tag":{"$$type":"string","value":"h1"},"title":{"$$type":"html-v3","value":{"content":{"$$type":"string","value":"Transforming Ideas<br>into Stunning<br>Digital Experiences"},"children":[]}},"link":{"$$type":"link","value":[]}},"elements":[],"isInner":false,"widgetType":"e-heading","elType":"widget","styles":{"e-37b88a51-1396f18":{"id":"e-37b88a51-1396f18","label":"local","type":"class","variants":[{"meta":{"breakpoint":"desktop","state":null},"props":{"font-size":{"$$type":"size","value":{"unit":"px","size":50}}},"custom_css":null},{"meta":{"breakpoint":"tablet","state":null},"props":{"font-size":{"$$type":"size","value":{"unit":"px","size":40}}},"custom_css":null}]}},"interactions":[],"editor_settings":[],"version":"0.0"},{"id":"3c4bff75","settings":{"editor":"<p>We craft professional websites, logos, and marketing campaigns that make your business shine.<\/p>","_element_width":"initial","_element_custom_width":{"unit":"%","size":78.596000000000004},"_flex_size":"none","__globals__":{"text_color":"globals\/colors?id=astglobalcolor3"}},"elements":[],"isInner":false,"widgetType":"text-editor","elType":"widget"},{"id":"6a9d715c","settings":{"classes":{"$$type":"classes","value":["e-6a9d715c-63adf58"]}},"elements":[{"id":"76922b47","settings":{"classes":{"$$type":"classes","value":["e-76922b47-57e2c6d","g-7a3ce83"]},"text":{"$$type":"html-v3","value":{"content":{"$$type":"string","value":"Get a Free Quote"},"children":[]}},"link":{"$$type":"link","value":{"destination":{"$$type":"url","value":"#services-section"}}}},"elements":[],"isInner":false,"widgetType":"e-button","elType":"widget","styles":{"e-76922b47-57e2c6d":{"id":"e-76922b47-57e2c6d","label":"local","type":"class","variants":[{"meta":{"breakpoint":"desktop","state":null},"props":{"padding":{"$$type":"dimensions","value":[]},"background":{"$$type":"background","value":{"color":{"$$type":"global-color-variable","value":"e-gv-4edbd6c"}}},"transition":{"$$type":"transition","value":[{"$$type":"selection-size","value":{"selection":{"$$type":"key-value","value":{"key":{"$$type":"string","value":"All properties"},"value":{"$$type":"string","value":"all"}}},"size":{"$$type":"size","value":{"unit":"ms","size":300}}}}]}},"custom_css":null},{"meta":{"breakpoint":"desktop","state":"hover"},"props":{"position":{"$$type":"string","value":"static"},"box-shadow":{"$$type":"box-shadow","value":[{"$$type":"shadow","value":{"hOffset":{"$$type":"size","value":{"unit":"px","size":0}},"vOffset":{"$$type":"size","value":{"unit":"px","size":5}},"blur":{"$$type":"size","value":{"unit":"px","size":10}},"spread":{"$$type":"size","value":{"unit":"px","size":0}},"color":{"$$type":"global-color-variable","value":"e-gv-a85b0c5"}}}]},"transform":{"$$type":"transform","value":{"transform-functions":{"$$type":"transform-functions","value":[{"$$type":"transform-move","value":{"x":{"$$type":"size","value":{"unit":"px","size":0}},"y":{"$$type":"size","value":{"unit":"px","size":-3}},"z":{"$$type":"size","value":{"unit":"px","size":0}}}}]}}}},"custom_css":null}]}},"interactions":[],"editor_settings":[],"version":"0.0"},{"id":"2d6beed8","settings":{"classes":{"$$type":"classes","value":["g-b4f75b3"]},"text":{"$$type":"html-v3","value":{"content":{"$$type":"string","value":"See Our Work"},"children":[]}},"link":{"$$type":"link","value":{"destination":{"$$type":"url","value":"#portfolio-section"}}}},"elements":[],"isInner":false,"widgetType":"e-button","elType":"widget","styles":[],"interactions":[],"editor_settings":[],"version":"0.0"}],"isInner":false,"elType":"e-div-block","styles":{"e-6a9d715c-63adf58":{"id":"e-6a9d715c-63adf58","label":"local","type":"class","variants":[{"meta":{"breakpoint":"desktop","state":null},"props":{"padding":{"$$type":"size","value":{"unit":"px","size":0}},"display":{"$$type":"string","value":"flex"},"gap":{"$$type":"size","value":{"unit":"px","size":32}}},"custom_css":null}]}},"interactions":[],"editor_settings":[],"version":"0.0"}],"isInner":false,"elType":"e-flexbox","styles":{"e-50e10dba-2c1e927":{"id":"e-50e10dba-2c1e927","label":"local","type":"class","variants":[{"meta":{"breakpoint":"desktop","state":null},"props":{"flex-direction":{"$$type":"string","value":"column"},"gap":{"$$type":"size","value":{"unit":"px","size":20}},"justify-content":{"$$type":"string","value":"center"}},"custom_css":null}]}},"interactions":[],"editor_settings":[],"version":"0.0"},{"id":"64583908","settings":{"classes":{"$$type":"classes","value":["e-64583908-e301e36"]},"image":{"$$type":"image","value":{"src":{"$$type":"image-src","value":{"id":{"$$type":"image-attachment-id","value":35},"url":{"$$type":"url","value":"http:\/\/brightspark.local\/wp-content\/uploads\/2026\/04\/woman-executive-work-scaled.jpg"}}}}},"link":{"$$type":"link","value":[]},"_cssid":{"$$type":"string","value":"img-hero"}},"elements":[],"isInner":false,"widgetType":"e-image","elType":"widget","styles":{"e-64583908-e301e36":{"id":"e-64583908-e301e36","label":"local","type":"class","variants":[{"meta":{"breakpoint":"desktop","state":null},"props":{"width":{"$$type":"size","value":{"unit":"%","size":65}},"border-radius":{"$$type":"border-radius","value":{"start-start":{"$$type":"size","value":{"unit":"px","size":32}},"start-end":{"$$type":"size","value":{"unit":"px","size":0}},"end-start":{"$$type":"size","value":{"unit":"px","size":0}},"end-end":{"$$type":"size","value":{"unit":"px","size":32}}}},"box-shadow":{"$$type":"box-shadow","value":[{"$$type":"shadow","value":{"hOffset":{"$$type":"size","value":{"unit":"px","size":0}},"vOffset":{"$$type":"size","value":{"unit":"px","size":10}},"blur":{"$$type":"size","value":{"unit":"px","size":20}},"spread":{"$$type":"size","value":{"unit":"px","size":0}},"color":{"$$type":"color","value":"#e4b6a4"}}}]},"backdrop-filter":{"$$type":"backdrop-filter","value":[]},"transition":{"$$type":"transition","value":[]}},"custom_css":null},{"meta":{"breakpoint":"tablet","state":null},"props":{"width":{"$$type":"size","value":{"unit":"%","size":80}}},"custom_css":null},{"meta":{"breakpoint":"mobile","state":null},"props":{"display":{"$$type":"string","value":"none"}},"custom_css":null}]}},"interactions":[],"editor_settings":[],"version":"0.0"}],"isInner":false,"elType":"container"}],"page_settings":{"hide_title":"yes","background_background":"classic","__globals__":{"background_color":""},"background_color":"#FFFFFF"},"version":"0.4","title":"HERO","type":"container","global_classes":{"items":{"g-7a3ce83":{"id":"g-7a3ce83","type":"class","label":"btn-1","variants":[{"meta":{"breakpoint":"desktop","state":null},"props":{"color":{"$$type":"global-color-variable","value":"e-gv-88facb4"},"padding":{"$$type":"dimensions","value":{"block-start":{"$$type":"size","value":{"size":12,"unit":"px"}},"inline-end":{"$$type":"size","value":{"size":24,"unit":"px"}},"block-end":{"$$type":"size","value":{"size":12,"unit":"px"}},"inline-start":{"$$type":"size","value":{"size":24,"unit":"px"}}}},"border-radius":{"$$type":"size","value":{"size":32,"unit":"px"}},"transition":{"$$type":"transition","value":[]}},"custom_css":null},{"meta":{"breakpoint":"tablet","state":null},"props":{"font-size":{"$$type":"size","value":{"size":14,"unit":"px"}}},"custom_css":null},{"meta":{"breakpoint":"mobile","state":null},"props":{"font-weight":{"$$type":"string","value":"700"},"font-size":{"$$type":"size","value":{"size":12,"unit":"px"}},"padding":{"$$type":"dimensions","value":{"block-start":{"$$type":"size","value":{"size":12,"unit":"px"}},"block-end":{"$$type":"size","value":{"size":12,"unit":"px"}},"inline-end":{"$$type":"size","value":{"size":24,"unit":"px"}},"inline-start":{"$$type":"size","value":{"size":24,"unit":"px"}}}},"align-self":{"$$type":"string","value":"center"}},"custom_css":null}]},"g-b4f75b3":{"id":"g-b4f75b3","type":"class","label":"btn-2","variants":[{"meta":{"breakpoint":"desktop","state":null},"props":{"color":{"$$type":"global-color-variable","value":"e-gv-6836274"},"border-radius":{"$$type":"size","value":{"size":32,"unit":"px"}},"border-width":{"$$type":"size","value":{"size":2,"unit":"px"}},"border-color":{"$$type":"global-color-variable","value":"e-gv-6836274"},"border-style":{"$$type":"string","value":"solid"},"background":{"$$type":"background","value":{"color":{"$$type":"color","value":"#04384200"}}},"transition":{"$$type":"transition","value":[{"$$type":"selection-size","value":{"selection":{"$$type":"key-value","value":{"key":{"$$type":"string","value":"All properties"},"value":{"$$type":"string","value":"all"}}},"size":{"$$type":"size","value":{"size":300,"unit":"ms"}}}}]}},"custom_css":null},{"meta":{"breakpoint":"desktop","state":"hover"},"props":{"color":{"$$type":"global-color-variable","value":"e-gv-e60bc0c"},"border-color":{"$$type":"global-color-variable","value":"e-gv-6836274"},"background":{"$$type":"background","value":{"color":{"$$type":"global-color-variable","value":"e-gv-6836274"}}},"box-shadow":{"$$type":"box-shadow","value":[]},"transform":{"$$type":"transform","value":{"transform-functions":{"$$type":"transform-functions","value":[{"$$type":"transform-move","value":{"x":{"$$type":"size","value":{"size":0,"unit":"px"}},"y":{"$$type":"size","value":{"size":-3,"unit":"px"}},"z":{"$$type":"size","value":{"size":0,"unit":"px"}}}}]}}}},"custom_css":null},{"meta":{"breakpoint":"mobile","state":null},"props":{"font-size":{"$$type":"size","value":{"size":12,"unit":"px"}}},"custom_css":null}]}},"order":["g-7a3ce83","g-b4f75b3"]},"global_variables":{"data":{"e-gv-4edbd6c":{"type":"global-color-variable","label":"naranja-500","value":"#FF4700","order":4,"updated_at":"2026-04-14 13:41:17"},"e-gv-a85b0c5":{"type":"global-color-variable","label":"naranja-300","value":"#FF8A5C","order":3,"deleted_at":"2026-04-14 13:41:17"},"e-gv-88facb4":{"label":"neutral-10","value":"#F1F3F3","order":10,"type":"global-color-variable","created_at":"2026-04-14 13:41:17","updated_at":"2026-04-14 13:41:17"},"e-gv-6836274":{"label":"blue-80","value":"#043943","order":9,"type":"global-color-variable","created_at":"2026-04-14 13:41:17","updated_at":"2026-04-14 13:41:17"},"e-gv-e60bc0c":{"label":"blue-10","value":"#E7FAFE","order":6,"type":"global-color-variable","created_at":"2026-04-14 13:41:17","updated_at":"2026-04-14 13:41:17"}},"watermark":0,"version":1}}